Metadata-Version: 2.1
Name: Sentimatrix
Version: 0.1.7
Summary: Advanced sentiment analysis platform for text, web content, audio data and Image data
Home-page: https://github.com/Siddharth-magesh/Sentimatrix
Author: Siddharth Magesh
Author-email: siddharthmagesh007@gmail.com
Classifier: Programming Language :: Python :: 3
Classifier: License :: OSI Approved :: MIT License
Classifier: Operating System :: OS Independent
Requires-Python: >=3.10
License-File: LICENSE
Requires-Dist: numpy==1.26.4
Requires-Dist: transformers
Requires-Dist: Pillow
Requires-Dist: torch==2.3.1
Requires-Dist: groq
Requires-Dist: openai
Requires-Dist: deep-translator
Requires-Dist: matplotlib
Requires-Dist: seaborn
Requires-Dist: pandas
Requires-Dist: SpeechRecognition
Requires-Dist: requests
Requires-Dist: beautifulsoup4
Requires-Dist: accelerate
Requires-Dist: selenium
Requires-Dist: praw
Requires-Dist: youtube-transcript-api
Requires-Dist: google-api-python-client
